dojo/__init__.py
dojo/api.py
dojo/api_multi.py
dojo/development_environment.py
dojo/dojo_group.py
dojo/engagement.py
dojo/finding.py
dojo/import_scan.py
dojo/jira_findings_mapping.py
dojo/jira_instance.py
dojo/jira_product_configuration.py
dojo/product.py
dojo/product_type.py
dojo/risk_acceptance.py
dojo/stub_finding.py
dojo/test.py
dojo/test_type.py
dojo/write_chain.py
dojo_truant-2024.2.7.post1.dist-info/LICENSE.txt
dojo_truant-2024.2.7.post1.dist-info/METADATA
dojo_truant-2024.2.7.post1.dist-info/WHEEL
dojo_truant-2024.2.7.post1.dist-info/top_level.txt
dojo_truant-2024.2.7.post1.dist-info/RECORD
