Metadata-Version: 2.1
Name: dojo_truant
Version: 2024.2.7.post1
Summary: A minimal client for deject dojo to be used by me in my projects. Most functionality should be absent.
Author-email: Chris Halbersma <chalbersma@auditboard.com>
License: BSD-3-Clause
Keywords: defectDojo
Classifier: Programming Language :: Python :: 3
Requires-Python: >=3.11
License-File: LICENSE.txt
Requires-Dist: requests
Requires-Dist: pyjq
Requires-Dist: json-fix
